{"NODTA":"RGBA(163, 180, 183,1)","CURSR":"RGBA(235, 125, 54,1)","CHBLK":"RGBA(7, 7, 7,1)","CHGRD":"RGBA(125, 137, 140,1)","CHGRF":"RGBA(163, 180, 183,1)","CHRED":"RGBA(241, 84, 105,1)","CHGRN":"RGBA(104, 228, 86,1)","CHYLW":"RGBA(244, 218, 72,1)","CHMGD":"RGBA(197, 69, 195,1)","CHMGF":"RGBA(211, 166, 233,1)","CHBRN":"RGBA(177, 145, 57,1)","CHWHT":"RGBA(212, 234, 238,1)","SCLBR":"RGBA(235, 125, 54,1)","CHCOR":"RGBA(235, 125, 54,1)","LITRD":"RGBA(241, 84, 105,1)","LITGN":"RGBA(104, 228, 86,1)","LITYW":"RGBA(244, 218, 72,1)","ISDNG":"RGBA(197, 69, 195,1)","DNGHL":"RGBA(241, 84, 105,1)","TRFCD":"RGBA(197, 69, 195,1)","TRFCF":"RGBA(211, 166, 233,1)","LANDA":"RGBA(201, 185, 122,1)","LANDF":"RGBA(139, 102, 31,1)","CSTLN":"RGBA(82, 90, 92,1)","SNDG1":"RGBA(125, 137, 140,1)","SNDG2":"RGBA(7, 7, 7,1)","DEPSC":"RGBA(82, 90, 92,1)","DEPCN":"RGBA(125, 137, 140,1)","DEPDW":"RGBA(212, 234, 238,1)","DEPMD":"RGBA(186, 213, 225,1)","DEPMS":"RGBA(152, 197, 242,1)","DEPVS":"RGBA(115, 182, 239,1)","DEPIT":"RGBA(131, 178, 149,1)","RADHI":"RGBA(104, 228, 86,1)","RADLO":"RGBA(63, 138, 52,1)","ARPAT":"RGBA(63, 165, 111,1)","NINFO":"RGBA(235, 125, 54,1)","RESBL":"RGBA(58, 120, 240,1)","ADINF":"RGBA(178, 159, 52,1)","RESGR":"RGBA(125, 137, 140,1)","SHIPS":"RGBA(7, 7, 7,1)","PSTRK":"RGBA(7, 7, 7,1)","SYTRK":"RGBA(125, 137, 140,1)","PLRTE":"RGBA(220, 64, 37,1)","APLRT":"RGBA(235, 125, 54,1)","UINFD":"RGBA(7, 7, 7,1)","UINFF":"RGBA(125, 137, 140,1)","UIBCK":"RGBA(212, 234, 238,1)","UIAFD":"RGBA(115, 182, 239,1)","UINFR":"RGBA(241, 84, 105,1)","UINFG":"RGBA(104, 228, 86,1)","UINFO":"RGBA(235, 125, 54,1)","UINFB":"RGBA(58, 120, 240,1)","UINFM":"RGBA(197, 69, 195,1)","UIBDR":"RGBA(125, 137, 140,1)","UIAFF":"RGBA(201, 185, 122,1)","OUTLW":"RGBA(7, 7, 7,1)","OUTLL":"RGBA(201, 185, 122,1)","RES01":"RGBA(163, 180, 183,1)","RES02":"RGBA(163, 180, 183,1)","RES03":"RGBA(163, 180, 183,1)","BKAJ1":"RGBA(7, 7, 7,1)","BKAJ2":"RGBA(35, 39, 40,1)"}